nanda_arch/__init__.py
nanda_arch/backends/__init__.py
nanda_arch/backends/apps.py
nanda_arch/backends/cli.py
nanda_arch/core/__init__.py
nanda_arch/core/base.py
nanda_arch/templates/__init__.template
nanda_arch/templates/apps.template
nanda_arch/templates/config.template
nanda_arch/templates/core.template
nanda_arch/templates/env.template
nanda_arch/templates/gitignore.template
nanda_arch/templates/main.template
nanda_arch/templates/models.template
nanda_arch/templates/router.template
nanda_arch/templates/security.template
nanda_arch/templates/settings.template
nanda_arch-1.0.13.dist-info/METADATA
nanda_arch-1.0.13.dist-info/WHEEL
nanda_arch-1.0.13.dist-info/entry_points.txt
nanda_arch-1.0.13.dist-info/RECORD
