Metadata-Version: 2.1
Name: nanda_arch
Version: 1.0.13
Summary: An opinionated backend framework, built on FastAPI and Tortoise ORM, for rapid and structured API development.
Home-page: https://github.com/Jefferson5286/nanda-arch.git
License: MIT
Keywords: fastapi,framework,tortoise-orm,async,api,rest
Author: Jeffers
Author-email: jeffersonlima5286@gmail.com
Requires-Python: >=3.13,<4.0
Classifier: Development Status :: 4 - Beta
Classifier: Framework :: FastAPI
Classifier: Intended Audience :: Developers
Classifier: License :: OSI Approved :: MIT License
Classifier: Programming Language :: Python :: 3
Classifier: Programming Language :: Python :: 3.13
Classifier: Topic :: Software Development :: Libraries :: Application Frameworks
Requires-Dist: aerich (>=0.9.1,<0.10.0)
Requires-Dist: bcrypt (>=4.3.0,<5.0.0)
Requires-Dist: fastapi[all] (>=0.116.0,<0.117.0)
Requires-Dist: libcst (>=1.8.2,<2.0.0)
Requires-Dist: passlib (>=1.7.4,<2.0.0)
Requires-Dist: python-decouple (>=3.8,<4.0)
Requires-Dist: python-jose[cryptography] (>=3.5.0,<4.0.0)
Requires-Dist: tomlkit (>=0.13.3,<0.14.0)
Requires-Dist: tortoise-orm (>=0.25.1,<0.26.0)
Requires-Dist: typer (>=0.16.0,<0.17.0)
Project-URL: Repository, https://github.com/Jefferson5286/nanda-arch.git
